{
    "bindings": [
      {
        "authLevel": "anonymous",
        "name": "req",
        "type": "httpTrigger",
        "direction": "in",
        "methods": [
          "get"
        ],
        "route": "activities"
      },
      {
        "name": "$return",
        "type": "http",
        "direction": "out"
      },
      {
        "type": "documentDB",
        "name": "documents",
        "databaseName": "Yarana",
        "collectionName": "Activities",
        "connection": "yarana_DOCUMENTDB",
        "direction": "in"
      }
    ],
    "disabled": false
  }